{"begin": "1642098919.466932", "end": "1642098919.910567", "request_id": "a12af83e-e8f8-4736-bca6-92eda15cdd12", "is_cold": false, "result": {"output": {"result": {"idx": 817, "class": "sports_car"}, "measurement": {"download_time": 147110.0, "compute_time": 1171497.0, "model_time": 744616.0, "model_download_time": 128719.0, "madvise_time": 252844.0, "handler_time": 1571502.0}}}}{"begin": "1642104076.933664", "end": "1642104077.345344", "request_id": "69b93c26-fa05-4f99-9c21-8b4e6d6a4792", "is_cold": false, "result": {"output": {"result": {"idx": 817, "class": "sports_car"}, "measurement": {"download_time": 152406.0, "compute_time": 1032465.0, "model_time": 764793.0, "model_download_time": 133243.0, "madvise_time": 173077.0, "handler_time": 1357997.0}}}}