{"begin": "1642098869.128579", "end": "1642098869.929825", "request_id": "ebfee849-db1c-46f2-94a8-93822f29c7f3", "is_cold": false, "result": {"output": {"result": {"idx": 817, "class": "sports_car"}, "measurement": {"download_time": 159995.0, "compute_time": 1044228.0, "model_time": 728939.0, "model_download_time": 139987.0, "madvise_time": 237632.0, "handler_time": 1441903.0}}}}{"begin": "1642104028.317443", "end": "1642104028.723644", "request_id": "983fcc7a-cf14-4f2f-b3b0-279007023f09", "is_cold": false, "result": {"output": {"result": {"idx": 817, "class": "sports_car"}, "measurement": {"download_time": 154078.0, "compute_time": 995899.0, "model_time": 738322.0, "model_download_time": 135857.0, "madvise_time": 159951.0, "handler_time": 1309976.0}}}}